{"nodes": [{"id": "c_users_abhra_onedrive_documents_vaaniarc_server_utils_uploadfiles_js", "label": "uploadFiles.js", "file_type": "code", "source_file": "C:\\Users\\abhra\\OneDrive\\Documents\\vaaniArc\\server\\utils\\uploadFiles.js", "source_location": "L1"}, {"id": "uploadfiles_ensureuploadsdirectory", "label": "ensureUploadsDirectory()", "file_type": "code", "source_file": "C:\\Users\\abhra\\OneDrive\\Documents\\vaaniArc\\server\\utils\\uploadFiles.js", "source_location": "L6"}, {"id": "uploadfiles_sanitizestoredfilename", "label": "sanitizeStoredFilename()", "file_type": "code", "source_file": "C:\\Users\\abhra\\OneDrive\\Documents\\vaaniArc\\server\\utils\\uploadFiles.js", "source_location": "L11"}, {"id": "uploadfiles_resolvestoredfilepath", "label": "resolveStoredFilePath()", "file_type": "code", "source_file": "C:\\Users\\abhra\\OneDrive\\Documents\\vaaniArc\\server\\utils\\uploadFiles.js", "source_location": "L13"}, {"id": "uploadfiles_buildattachmenturl", "label": "buildAttachmentUrl()", "file_type": "code", "source_file": "C:\\Users\\abhra\\OneDrive\\Documents\\vaaniArc\\server\\utils\\uploadFiles.js", "source_location": "L18"}, {"id": "uploadfiles_buildavatarurl", "label": "buildAvatarUrl()", "file_type": "code", "source_file": "C:\\Users\\abhra\\OneDrive\\Documents\\vaaniArc\\server\\utils\\uploadFiles.js", "source_location": "L19"}, {"id": "uploadfiles_buildlegacyuploadurl", "label": "buildLegacyUploadUrl()", "file_type": "code", "source_file": "C:\\Users\\abhra\\OneDrive\\Documents\\vaaniArc\\server\\utils\\uploadFiles.js", "source_location": "L20"}], "edges": [{"source": "c_users_abhra_onedrive_documents_vaaniarc_server_utils_uploadfiles_js", "target": "uploadfiles_ensureuploadsdirectory", "relation": "contains", "confidence": "EXTRACTED", "source_file": "C:\\Users\\abhra\\OneDrive\\Documents\\vaaniArc\\server\\utils\\uploadFiles.js", "source_location": "L6", "weight": 1.0}, {"source": "c_users_abhra_onedrive_documents_vaaniarc_server_utils_uploadfiles_js", "target": "uploadfiles_sanitizestoredfilename", "relation": "contains", "confidence": "EXTRACTED", "source_file": "C:\\Users\\abhra\\OneDrive\\Documents\\vaaniArc\\server\\utils\\uploadFiles.js", "source_location": "L11", "weight": 1.0}, {"source": "c_users_abhra_onedrive_documents_vaaniarc_server_utils_uploadfiles_js", "target": "uploadfiles_resolvestoredfilepath", "relation": "contains", "confidence": "EXTRACTED", "source_file": "C:\\Users\\abhra\\OneDrive\\Documents\\vaaniArc\\server\\utils\\uploadFiles.js", "source_location": "L13", "weight": 1.0}, {"source": "c_users_abhra_onedrive_documents_vaaniarc_server_utils_uploadfiles_js", "target": "uploadfiles_buildattachmenturl", "relation": "contains", "confidence": "EXTRACTED", "source_file": "C:\\Users\\abhra\\OneDrive\\Documents\\vaaniArc\\server\\utils\\uploadFiles.js", "source_location": "L18", "weight": 1.0}, {"source": "c_users_abhra_onedrive_documents_vaaniarc_server_utils_uploadfiles_js", "target": "uploadfiles_buildavatarurl", "relation": "contains", "confidence": "EXTRACTED", "source_file": "C:\\Users\\abhra\\OneDrive\\Documents\\vaaniArc\\server\\utils\\uploadFiles.js", "source_location": "L19", "weight": 1.0}, {"source": "c_users_abhra_onedrive_documents_vaaniarc_server_utils_uploadfiles_js", "target": "uploadfiles_buildlegacyuploadurl", "relation": "contains", "confidence": "EXTRACTED", "source_file": "C:\\Users\\abhra\\OneDrive\\Documents\\vaaniArc\\server\\utils\\uploadFiles.js", "source_location": "L20", "weight": 1.0}, {"source": "uploadfiles_resolvestoredfilepath", "target": "uploadfiles_ensureuploadsdirectory", "relation": "calls", "confidence": "EXTRACTED", "source_file": "C:\\Users\\abhra\\OneDrive\\Documents\\vaaniArc\\server\\utils\\uploadFiles.js", "source_location": "L14", "weight": 1.0}, {"source": "uploadfiles_resolvestoredfilepath", "target": "uploadfiles_sanitizestoredfilename", "relation": "calls", "confidence": "EXTRACTED", "source_file": "C:\\Users\\abhra\\OneDrive\\Documents\\vaaniArc\\server\\utils\\uploadFiles.js", "source_location": "L15", "weight": 1.0}, {"source": "uploadfiles_buildattachmenturl", "target": "uploadfiles_sanitizestoredfilename", "relation": "calls", "confidence": "EXTRACTED", "source_file": "C:\\Users\\abhra\\OneDrive\\Documents\\vaaniArc\\server\\utils\\uploadFiles.js", "source_location": "L18", "weight": 1.0}, {"source": "uploadfiles_buildavatarurl", "target": "uploadfiles_sanitizestoredfilename", "relation": "calls", "confidence": "EXTRACTED", "source_file": "C:\\Users\\abhra\\OneDrive\\Documents\\vaaniArc\\server\\utils\\uploadFiles.js", "source_location": "L19", "weight": 1.0}, {"source": "uploadfiles_buildlegacyuploadurl", "target": "uploadfiles_sanitizestoredfilename", "relation": "calls", "confidence": "EXTRACTED", "source_file": "C:\\Users\\abhra\\OneDrive\\Documents\\vaaniArc\\server\\utils\\uploadFiles.js", "source_location": "L20", "weight": 1.0}], "raw_calls": [{"caller_nid": "uploadfiles_ensureuploadsdirectory", "callee": "mkdirSync", "source_file": "C:\\Users\\abhra\\OneDrive\\Documents\\vaaniArc\\server\\utils\\uploadFiles.js", "source_location": "L7"}, {"caller_nid": "uploadfiles_sanitizestoredfilename", "callee": "basename", "source_file": "C:\\Users\\abhra\\OneDrive\\Documents\\vaaniArc\\server\\utils\\uploadFiles.js", "source_location": "L11"}, {"caller_nid": "uploadfiles_sanitizestoredfilename", "callee": "trim", "source_file": "C:\\Users\\abhra\\OneDrive\\Documents\\vaaniArc\\server\\utils\\uploadFiles.js", "source_location": "L11"}, {"caller_nid": "uploadfiles_sanitizestoredfilename", "callee": "String", "source_file": "C:\\Users\\abhra\\OneDrive\\Documents\\vaaniArc\\server\\utils\\uploadFiles.js", "source_location": "L11"}, {"caller_nid": "uploadfiles_resolvestoredfilepath", "callee": "join", "source_file": "C:\\Users\\abhra\\OneDrive\\Documents\\vaaniArc\\server\\utils\\uploadFiles.js", "source_location": "L13"}]}