{"nodes": [{"id": "c_users_abhra_onedrive_documents_vaaniarc_scripts_wait_for_backend_js", "label": "wait-for-backend.js", "file_type": "code", "source_file": "C:\\Users\\abhra\\OneDrive\\Documents\\vaaniArc\\scripts\\wait-for-backend.js", "source_location": "L1"}, {"id": "wait_for_backend_parsepositiveint", "label": "parsePositiveInt()", "file_type": "code", "source_file": "C:\\Users\\abhra\\OneDrive\\Documents\\vaaniArc\\scripts\\wait-for-backend.js", "source_location": "L7"}, {"id": "wait_for_backend_getwaitoptions", "label": "getWaitOptions()", "file_type": "code", "source_file": "C:\\Users\\abhra\\OneDrive\\Documents\\vaaniArc\\scripts\\wait-for-backend.js", "source_location": "L12"}, {"id": "wait_for_backend_requestonce", "label": "requestOnce()", "file_type": "code", "source_file": "C:\\Users\\abhra\\OneDrive\\Documents\\vaaniArc\\scripts\\wait-for-backend.js", "source_location": "L18"}, {"id": "wait_for_backend_sleep", "label": "sleep()", "file_type": "code", "source_file": "C:\\Users\\abhra\\OneDrive\\Documents\\vaaniArc\\scripts\\wait-for-backend.js", "source_location": "L32"}, {"id": "wait_for_backend_waitforbackend", "label": "waitForBackend()", "file_type": "code", "source_file": "C:\\Users\\abhra\\OneDrive\\Documents\\vaaniArc\\scripts\\wait-for-backend.js", "source_location": "L36"}], "edges": [{"source": "c_users_abhra_onedrive_documents_vaaniarc_scripts_wait_for_backend_js", "target": "wait_for_backend_parsepositiveint", "relation": "contains", "confidence": "EXTRACTED", "source_file": "C:\\Users\\abhra\\OneDrive\\Documents\\vaaniArc\\scripts\\wait-for-backend.js", "source_location": "L7", "weight": 1.0}, {"source": "c_users_abhra_onedrive_documents_vaaniarc_scripts_wait_for_backend_js", "target": "wait_for_backend_getwaitoptions", "relation": "contains", "confidence": "EXTRACTED", "source_file": "C:\\Users\\abhra\\OneDrive\\Documents\\vaaniArc\\scripts\\wait-for-backend.js", "source_location": "L12", "weight": 1.0}, {"source": "c_users_abhra_onedrive_documents_vaaniarc_scripts_wait_for_backend_js", "target": "wait_for_backend_requestonce", "relation": "contains", "confidence": "EXTRACTED", "source_file": "C:\\Users\\abhra\\OneDrive\\Documents\\vaaniArc\\scripts\\wait-for-backend.js", "source_location": "L18", "weight": 1.0}, {"source": "c_users_abhra_onedrive_documents_vaaniarc_scripts_wait_for_backend_js", "target": "wait_for_backend_sleep", "relation": "contains", "confidence": "EXTRACTED", "source_file": "C:\\Users\\abhra\\OneDrive\\Documents\\vaaniArc\\scripts\\wait-for-backend.js", "source_location": "L32", "weight": 1.0}, {"source": "c_users_abhra_onedrive_documents_vaaniarc_scripts_wait_for_backend_js", "target": "wait_for_backend_waitforbackend", "relation": "contains", "confidence": "EXTRACTED", "source_file": "C:\\Users\\abhra\\OneDrive\\Documents\\vaaniArc\\scripts\\wait-for-backend.js", "source_location": "L36", "weight": 1.0}, {"source": "wait_for_backend_getwaitoptions", "target": "wait_for_backend_parsepositiveint", "relation": "calls", "confidence": "EXTRACTED", "source_file": "C:\\Users\\abhra\\OneDrive\\Documents\\vaaniArc\\scripts\\wait-for-backend.js", "source_location": "L14", "weight": 1.0}, {"source": "wait_for_backend_waitforbackend", "target": "wait_for_backend_getwaitoptions", "relation": "calls", "confidence": "EXTRACTED", "source_file": "C:\\Users\\abhra\\OneDrive\\Documents\\vaaniArc\\scripts\\wait-for-backend.js", "source_location": "L37", "weight": 1.0}, {"source": "wait_for_backend_waitforbackend", "target": "wait_for_backend_requestonce", "relation": "calls", "confidence": "EXTRACTED", "source_file": "C:\\Users\\abhra\\OneDrive\\Documents\\vaaniArc\\scripts\\wait-for-backend.js", "source_location": "L50", "weight": 1.0}, {"source": "wait_for_backend_waitforbackend", "target": "wait_for_backend_sleep", "relation": "calls", "confidence": "EXTRACTED", "source_file": "C:\\Users\\abhra\\OneDrive\\Documents\\vaaniArc\\scripts\\wait-for-backend.js", "source_location": "L61", "weight": 1.0}], "raw_calls": [{"caller_nid": "wait_for_backend_parsepositiveint", "callee": "parseInt", "source_file": "C:\\Users\\abhra\\OneDrive\\Documents\\vaaniArc\\scripts\\wait-for-backend.js", "source_location": "L8"}, {"caller_nid": "wait_for_backend_parsepositiveint", "callee": "String", "source_file": "C:\\Users\\abhra\\OneDrive\\Documents\\vaaniArc\\scripts\\wait-for-backend.js", "source_location": "L8"}, {"caller_nid": "wait_for_backend_parsepositiveint", "callee": "isInteger", "source_file": "C:\\Users\\abhra\\OneDrive\\Documents\\vaaniArc\\scripts\\wait-for-backend.js", "source_location": "L9"}, {"caller_nid": "wait_for_backend_waitforbackend", "callee": "now", "source_file": "C:\\Users\\abhra\\OneDrive\\Documents\\vaaniArc\\scripts\\wait-for-backend.js", "source_location": "L43"}, {"caller_nid": "wait_for_backend_waitforbackend", "callee": "now", "source_file": "C:\\Users\\abhra\\OneDrive\\Documents\\vaaniArc\\scripts\\wait-for-backend.js", "source_location": "L46"}, {"caller_nid": "wait_for_backend_waitforbackend", "callee": "log", "source_file": "C:\\Users\\abhra\\OneDrive\\Documents\\vaaniArc\\scripts\\wait-for-backend.js", "source_location": "L52"}, {"caller_nid": "wait_for_backend_waitforbackend", "callee": "now", "source_file": "C:\\Users\\abhra\\OneDrive\\Documents\\vaaniArc\\scripts\\wait-for-backend.js", "source_location": "L56"}, {"caller_nid": "wait_for_backend_waitforbackend", "callee": "error", "source_file": "C:\\Users\\abhra\\OneDrive\\Documents\\vaaniArc\\scripts\\wait-for-backend.js", "source_location": "L57"}, {"caller_nid": "wait_for_backend_waitforbackend", "callee": "error", "source_file": "C:\\Users\\abhra\\OneDrive\\Documents\\vaaniArc\\scripts\\wait-for-backend.js", "source_location": "L64"}, {"caller_nid": "wait_for_backend_waitforbackend", "callee": "exit", "source_file": "C:\\Users\\abhra\\OneDrive\\Documents\\vaaniArc\\scripts\\wait-for-backend.js", "source_location": "L65"}]}