{"nodes": [{"id": "c_users_abhra_onedrive_documents_vaaniarc_server_services_cacheservice_js", "label": "cacheService.js", "file_type": "code", "source_file": "C:\\Users\\abhra\\OneDrive\\Documents\\vaaniArc\\server\\services\\cacheService.js", "source_location": "L1"}, {"id": "cacheservice_buildrediskey", "label": "buildRedisKey()", "file_type": "code", "source_file": "C:\\Users\\abhra\\OneDrive\\Documents\\vaaniArc\\server\\services\\cacheService.js", "source_location": "L22"}, {"id": "cacheservice_serialize", "label": "serialize()", "file_type": "code", "source_file": "C:\\Users\\abhra\\OneDrive\\Documents\\vaaniArc\\server\\services\\cacheService.js", "source_location": "L24"}, {"id": "cacheservice_deserialize", "label": "deserialize()", "file_type": "code", "source_file": "C:\\Users\\abhra\\OneDrive\\Documents\\vaaniArc\\server\\services\\cacheService.js", "source_location": "L25"}, {"id": "cacheservice_cleanupmemorymap", "label": "cleanupMemoryMap()", "file_type": "code", "source_file": "C:\\Users\\abhra\\OneDrive\\Documents\\vaaniArc\\server\\services\\cacheService.js", "source_location": "L37"}, {"id": "cacheservice_ensureredisconnection", "label": "ensureRedisConnection()", "file_type": "code", "source_file": "C:\\Users\\abhra\\OneDrive\\Documents\\vaaniArc\\server\\services\\cacheService.js", "source_location": "L47"}, {"id": "cacheservice_deleterediskeysbyprefix", "label": "deleteRedisKeysByPrefix()", "file_type": "code", "source_file": "C:\\Users\\abhra\\OneDrive\\Documents\\vaaniArc\\server\\services\\cacheService.js", "source_location": "L112"}], "edges": [{"source": "c_users_abhra_onedrive_documents_vaaniarc_server_services_cacheservice_js", "target": "cacheservice_buildrediskey", "relation": "contains", "confidence": "EXTRACTED", "source_file": "C:\\Users\\abhra\\OneDrive\\Documents\\vaaniArc\\server\\services\\cacheService.js", "source_location": "L22", "weight": 1.0}, {"source": "c_users_abhra_onedrive_documents_vaaniarc_server_services_cacheservice_js", "target": "cacheservice_serialize", "relation": "contains", "confidence": "EXTRACTED", "source_file": "C:\\Users\\abhra\\OneDrive\\Documents\\vaaniArc\\server\\services\\cacheService.js", "source_location": "L24", "weight": 1.0}, {"source": "c_users_abhra_onedrive_documents_vaaniarc_server_services_cacheservice_js", "target": "cacheservice_deserialize", "relation": "contains", "confidence": "EXTRACTED", "source_file": "C:\\Users\\abhra\\OneDrive\\Documents\\vaaniArc\\server\\services\\cacheService.js", "source_location": "L25", "weight": 1.0}, {"source": "c_users_abhra_onedrive_documents_vaaniarc_server_services_cacheservice_js", "target": "cacheservice_cleanupmemorymap", "relation": "contains", "confidence": "EXTRACTED", "source_file": "C:\\Users\\abhra\\OneDrive\\Documents\\vaaniArc\\server\\services\\cacheService.js", "source_location": "L37", "weight": 1.0}, {"source": "c_users_abhra_onedrive_documents_vaaniarc_server_services_cacheservice_js", "target": "cacheservice_ensureredisconnection", "relation": "contains", "confidence": "EXTRACTED", "source_file": "C:\\Users\\abhra\\OneDrive\\Documents\\vaaniArc\\server\\services\\cacheService.js", "source_location": "L47", "weight": 1.0}, {"source": "c_users_abhra_onedrive_documents_vaaniarc_server_services_cacheservice_js", "target": "cacheservice_deleterediskeysbyprefix", "relation": "contains", "confidence": "EXTRACTED", "source_file": "C:\\Users\\abhra\\OneDrive\\Documents\\vaaniArc\\server\\services\\cacheService.js", "source_location": "L112", "weight": 1.0}, {"source": "cacheservice_deleterediskeysbyprefix", "target": "cacheservice_buildrediskey", "relation": "calls", "confidence": "EXTRACTED", "source_file": "C:\\Users\\abhra\\OneDrive\\Documents\\vaaniArc\\server\\services\\cacheService.js", "source_location": "L113", "weight": 1.0}], "raw_calls": [{"caller_nid": "cacheservice_serialize", "callee": "stringify", "source_file": "C:\\Users\\abhra\\OneDrive\\Documents\\vaaniArc\\server\\services\\cacheService.js", "source_location": "L24"}, {"caller_nid": "cacheservice_deserialize", "callee": "parse", "source_file": "C:\\Users\\abhra\\OneDrive\\Documents\\vaaniArc\\server\\services\\cacheService.js", "source_location": "L31"}, {"caller_nid": "cacheservice_cleanupmemorymap", "callee": "now", "source_file": "C:\\Users\\abhra\\OneDrive\\Documents\\vaaniArc\\server\\services\\cacheService.js", "source_location": "L38"}, {"caller_nid": "cacheservice_cleanupmemorymap", "callee": "entries", "source_file": "C:\\Users\\abhra\\OneDrive\\Documents\\vaaniArc\\server\\services\\cacheService.js", "source_location": "L40"}, {"caller_nid": "cacheservice_cleanupmemorymap", "callee": "getExpiresAt", "source_file": "C:\\Users\\abhra\\OneDrive\\Documents\\vaaniArc\\server\\services\\cacheService.js", "source_location": "L41"}, {"caller_nid": "cacheservice_cleanupmemorymap", "callee": "delete", "source_file": "C:\\Users\\abhra\\OneDrive\\Documents\\vaaniArc\\server\\services\\cacheService.js", "source_location": "L42"}, {"caller_nid": "cacheservice_ensureredisconnection", "callee": "createClient", "source_file": "C:\\Users\\abhra\\OneDrive\\Documents\\vaaniArc\\server\\services\\cacheService.js", "source_location": "L65"}, {"caller_nid": "cacheservice_ensureredisconnection", "callee": "on", "source_file": "C:\\Users\\abhra\\OneDrive\\Documents\\vaaniArc\\server\\services\\cacheService.js", "source_location": "L69"}, {"caller_nid": "cacheservice_ensureredisconnection", "callee": "on", "source_file": "C:\\Users\\abhra\\OneDrive\\Documents\\vaaniArc\\server\\services\\cacheService.js", "source_location": "L76"}, {"caller_nid": "cacheservice_ensureredisconnection", "callee": "on", "source_file": "C:\\Users\\abhra\\OneDrive\\Documents\\vaaniArc\\server\\services\\cacheService.js", "source_location": "L81"}, {"caller_nid": "cacheservice_ensureredisconnection", "callee": "catch", "source_file": "C:\\Users\\abhra\\OneDrive\\Documents\\vaaniArc\\server\\services\\cacheService.js", "source_location": "L86"}, {"caller_nid": "cacheservice_ensureredisconnection", "callee": "then", "source_file": "C:\\Users\\abhra\\OneDrive\\Documents\\vaaniArc\\server\\services\\cacheService.js", "source_location": "L86"}, {"caller_nid": "cacheservice_ensureredisconnection", "callee": "connect", "source_file": "C:\\Users\\abhra\\OneDrive\\Documents\\vaaniArc\\server\\services\\cacheService.js", "source_location": "L86"}, {"caller_nid": "cacheservice_deleterediskeysbyprefix", "callee": "scan", "source_file": "C:\\Users\\abhra\\OneDrive\\Documents\\vaaniArc\\server\\services\\cacheService.js", "source_location": "L118"}, {"caller_nid": "cacheservice_deleterediskeysbyprefix", "callee": "isArray", "source_file": "C:\\Users\\abhra\\OneDrive\\Documents\\vaaniArc\\server\\services\\cacheService.js", "source_location": "L124"}, {"caller_nid": "cacheservice_deleterediskeysbyprefix", "callee": "del", "source_file": "C:\\Users\\abhra\\OneDrive\\Documents\\vaaniArc\\server\\services\\cacheService.js", "source_location": "L126"}]}